LICENSE
README.md
setup.py
pyommlbuilder/__init__.py
pyommlbuilder/functions.py
pyommlbuilder/helpers.py
pyommlbuilder/main.py
pyommlbuilder.egg-info/PKG-INFO
pyommlbuilder.egg-info/SOURCES.txt
pyommlbuilder.egg-info/dependency_links.txt
pyommlbuilder.egg-info/top_level.txt