Metadata-Version: 2.1
Name: pyommlbuilder
Version: 0.0.2
Summary: A wrapper of OMML using Python Objects
Author: Charlie Yu
Author-email: imo.charlie@gmail.com
License-File: LICENSE
